geetest_captcha_solver/__init__.py
geetest_captcha_solver/api.py
geetest_captcha_solver/asyncplaywrightsolver.py
geetest_captcha_solver/asyncsolver.py
geetest_captcha_solver/captchatype.py
geetest_captcha_solver/download_crx.py
geetest_captcha_solver/downloader.py
geetest_captcha_solver/geometry.py
geetest_captcha_solver/launcher.py
geetest_captcha_solver/models.py
geetest_captcha_solver/nodriversolver.py
geetest_captcha_solver/playwrightsolver.py
geetest_captcha_solver/selectors.py
geetest_captcha_solver/seleniumsolver.py
geetest_captcha_solver/solver.py
geetest_captcha_solver/tests/__init__.py
geetest_captcha_solver/tests/test_api.py
geetest_captcha_solver/tests/test_asyncplaywrightsolver.py
geetest_captcha_solver/tests/test_download_crx.py
geetest_captcha_solver/tests/test_downloader.py
geetest_captcha_solver/tests/test_launcher.py
geetest_captcha_solver/tests/test_playwrightsolver.py
geetest_captcha_solver/tests/test_seleniumsolver.py
geetest_captcha_solver-0.0.1.dist-info/METADATA
geetest_captcha_solver-0.0.1.dist-info/WHEEL
geetest_captcha_solver-0.0.1.dist-info/top_level.txt
geetest_captcha_solver-0.0.1.dist-info/RECORD
